MANIFEST.in
README.rst
setup.py
metron/__init__.py
metron/activity.py
metron.egg-info/PKG-INFO
metron.egg-info/SOURCES.txt
metron.egg-info/dependency_links.txt
metron.egg-info/not-zip-safe
metron.egg-info/top_level.txt
metron/templates/metron/_adwords_conversion.html
metron/templates/metron/_gauges.html
metron/templates/metron/_google.html
metron/templates/metron/_mixpanel.html
metron/templatetags/__init__.py
metron/templatetags/metron_tags.py
metron/tests/__init__.py
metron/tests/models.py
metron/tests/tests.py
metron/tests/urls.py